mcp_resk-0.1.0.dist-info/licenses/LICENSE
mcp_resk-0.1.0.dist-info/licenses/Notice
resk_mcp/__init__.py
resk_mcp/auth.py
resk_mcp/config.py
resk_mcp/context.py
resk_mcp/dashboard.py
resk_mcp/schema_validation.py
resk_mcp/security.py
resk_mcp/server.py
resk_mcp/validation.py
mcp_resk-0.1.0.dist-info/METADATA
mcp_resk-0.1.0.dist-info/WHEEL
mcp_resk-0.1.0.dist-info/entry_points.txt
mcp_resk-0.1.0.dist-info/top_level.txt
mcp_resk-0.1.0.dist-info/RECORD
