Metadata-Version: 2.4
Name: mcp-resk
Version: 0.1.0
Summary: RESK-MCP is an open-source Python library designed to add a robust security and management layer over the official MCP Library.
Author-email: RESK Team <your.email@example.com>
License: MIT License
Project-URL: Homepage, https://github.com/your-username/mcp-resk
Project-URL: Bug Tracker, https://github.com/your-username/mcp-resk/issues
Classifier: Programming Language :: Python :: 3
Classifier: Programming Language :: Python :: 3.10
Classifier: License :: OSI Approved :: MIT License
Classifier: Operating System :: OS Independent
Classifier: Development Status :: 4 - Beta
Classifier: Intended Audience :: Developers
Classifier: Topic :: Software Development :: Libraries :: Python Modules
Requires-Python: >=3.10
License-File: LICENSE
License-File: Notice
Requires-Dist: fastapi>=0.115.12
Requires-Dist: mcp[cli]>=1.9.0
Requires-Dist: pydantic>=2.11.4
Requires-Dist: pyjwt[crypto]>=2.10.1
Requires-Dist: python-dotenv>=1.1.0
Requires-Dist: pyyaml>=6.0.2
Requires-Dist: requests>=2.32.3
Requires-Dist: slowapi>=0.1.9
Requires-Dist: types-pyyaml>=6.0.12.20250516
Requires-Dist: uvicorn>=0.34.2
Dynamic: license-file
